as_scraper/__init__.py
as_scraper/errors.py
as_scraper/exceptions.py
as_scraper/headers.py
as_scraper/scraper.py
as_scraper/crawlers/__init__.py
as_scraper/crawlers/crawler.py
as_scraper/crawlers/tree_crawler.py
as_scraper-2.5.1.dist-info/LICENSE
as_scraper-2.5.1.dist-info/METADATA
as_scraper-2.5.1.dist-info/WHEEL
as_scraper-2.5.1.dist-info/top_level.txt
as_scraper-2.5.1.dist-info/RECORD
