Metadata-Version: 2.1
Name: as-scraper
Version: 2.5.1
Summary: Python library for scraping with Selenium.
Home-page: https://github.com/Avila-Systems/as-scraper
Author: Alvaro Avila
Author-email: almiavicas@gmail.com
Project-URL: Github Project, https://github.com/Avila-Systems/as-scraper
Project-URL: Issue Tracker, https://github.com/Avila-Systems/as-scraper/issues
Classifier: Intended Audience :: Developers
Classifier: Programming Language :: Python
Classifier: Programming Language :: Python :: 3
Classifier: Operating System :: POSIX
Classifier: License :: OSI Approved :: MIT License
Classifier: Topic :: Software Development :: Libraries
Requires-Python: >=3.7
License-File: LICENSE
Requires-Dist: attrs <=23.0
Requires-Dist: selenium <=4.10
Requires-Dist: bs4
Requires-Dist: lxml
Requires-Dist: pandas
Requires-Dist: requests
Requires-Dist: tqdm
